epicsdev_simulated/__init__.py
epicsdev_simulated/simscope.py
epicsdev_simulated-0.1.0.dist-info/METADATA
epicsdev_simulated-0.1.0.dist-info/WHEEL
epicsdev_simulated-0.1.0.dist-info/licenses/LICENSE
epicsdev_simulated-0.1.0.dist-info/RECORD
